gradle.properties
hexdoc_ioticblocks/__gradle_version__.py
hexdoc_ioticblocks/__init__.py
hexdoc_ioticblocks/__version__.py
hexdoc_ioticblocks/_hooks.py
hexdoc_ioticblocks/py.typed
hexdoc_ioticblocks/_export/.gitignore
hexdoc_ioticblocks/_export/__init__.py
hexdoc_ioticblocks/_export/generated/__init__.py
hexdoc_ioticblocks/_export/generated/ioticblocks.hexdoc.json
hexdoc_ioticblocks/_export/generated/ioticblocks.patterns.hexdoc.json
hexdoc_ioticblocks/_export/generated/assets/hexcasting/patchouli_books/thehexbook/en_us/entries/patterns/readwrite_blocks.json5
hexdoc_ioticblocks/_export/generated/assets/ioticblocks/lang/en_us.flatten.json5
hexdoc_ioticblocks/_export/generated/assets/ioticblocks/lang/ru_ru.flatten.json5
hexdoc_ioticblocks/_export/generated/assets/ioticblocks/lang/zh_cn.flatten.json5
hexdoc_ioticblocks/_templates/__init__.py
hexdoc_ioticblocks-1.0.2.1.20.1.1.0.dist-info/METADATA
hexdoc_ioticblocks-1.0.2.1.20.1.1.0.dist-info/WHEEL
hexdoc_ioticblocks-1.0.2.1.20.1.1.0.dist-info/entry_points.txt
hexdoc_ioticblocks-1.0.2.1.20.1.1.0.dist-info/licenses/LICENSE
hexdoc_ioticblocks-1.0.2.1.20.1.1.0.dist-info/RECORD
