Metadata-Version: 2.4
Name: hexdoc-ioticblocks
Version: 1.0.2.1.20.1.1.0
Summary: Python web book docgen and hexdoc plugin for IoticBlocks.
Project-URL: Homepage, https://object-object.github.io/IoticBlocks
Project-URL: Source, https://github.com/object-Object/IoticBlocks
Author: object-Object
License-File: LICENSE
Keywords: hexdoc
Requires-Python: >=3.11
Requires-Dist: hexdoc-hexcasting~=0.11.2.1.0
Provides-Extra: dev
Requires-Dist: ruff~=0.11.2; extra == 'dev'
